paddy/__init__.py
paddy/argscmd.py
paddycmd-0.1.0.dist-info/METADATA
paddycmd-0.1.0.dist-info/WHEEL
paddycmd-0.1.0.dist-info/entry_points.txt
paddycmd-0.1.0.dist-info/top_level.txt
paddycmd-0.1.0.dist-info/RECORD
