Metadata-Version: 2.1
Name: paddycmd
Version: 0.1.0
Requires-Dist: easygui
Requires-Dist: argparse
